FixedWidthTextParser/Parser.py
FixedWidthTextParser/__init__.py
FixedWidthTextParser/Seismic/SpsParser.py
FixedWidthTextParser/Seismic/VibratorParser.py
FixedWidthTextParser/Seismic/__init__.py
tests/__init__.py
tests/test_parser.py
tests/test_sps_parser.py
tests/test_vibrator_parser.py
FixedWidthTextParser-0.4.1.dist-info/LICENSE
FixedWidthTextParser-0.4.1.dist-info/METADATA
FixedWidthTextParser-0.4.1.dist-info/WHEEL
FixedWidthTextParser-0.4.1.dist-info/top_level.txt
FixedWidthTextParser-0.4.1.dist-info/RECORD
