Metadata-Version: 2.1
Name: FixedWidthTextParser
Version: 0.4.1
Summary: Fixed width text parser
Home-page: https://github.com/mysiar/fixed-width-text-parser
Author: Piotr Synowiec
Author-email: psynowiec@gmail.com
License: UNKNOWN
Platform: UNKNOWN
Classifier: Programming Language :: Python :: 3
Classifier: License :: OSI Approved :: MIT License
Classifier: Operating System :: OS Independent
Requires-Python: >=3.6
